pp.connector.plone-1.0.0-py3.7-nspkg.pth
pp/client/plone/__init__.py
pp/client/plone/configure.zcml
pp/client/plone/header.txt
pp/client/plone/i18n.py
pp/client/plone/interfaces.py
pp/client/plone/logger.py
pp/client/plone/meta.zcml
pp/client/plone/service.py
pp/client/plone/zcml.py
pp/client/plone/browser/__init__.py
pp/client/plone/browser/configure.zcml
pp/client/plone/browser/controlpanel.py
pp/client/plone/browser/demo.py
pp/client/plone/browser/tests/__init__.py
pp/client/plone/profiles/default/browserlayer.xml
pp/client/plone/profiles/default/controlpanel.xml
pp/client/plone/profiles/default/metadata.xml
pp/client/plone/profiles/default/registry.xml
pp/client/plone/profiles/uninstall/readme.txt
pp/client/plone/resources_default/DejaVuSans-Bold.ttf
pp/client/plone/resources_default/DejaVuSans-BoldOblique.ttf
pp/client/plone/resources_default/DejaVuSans-Oblique.ttf
pp/client/plone/resources_default/DejaVuSans.ttf
pp/client/plone/resources_default/DejaVuSansCondensed-Bold.ttf
pp/client/plone/resources_default/DejaVuSansCondensed-BoldOblique.ttf
pp/client/plone/resources_default/DejaVuSansCondensed-Oblique.ttf
pp/client/plone/resources_default/DejaVuSansCondensed.ttf
pp/client/plone/resources_default/DejaVuSerif-Bold.ttf
pp/client/plone/resources_default/DejaVuSerif-BoldItalic.ttf
pp/client/plone/resources_default/DejaVuSerif-Italic.ttf
pp/client/plone/resources_default/DejaVuSerif.ttf
pp/client/plone/resources_default/base.css
pp/client/plone/resources_default/default.conversion
pp/client/plone/resources_default/fonts.css
pp/client/plone/resources_default/pdf_template.pt
pp.connector.plone-1.0.0.dist-info/METADATA
pp.connector.plone-1.0.0.dist-info/WHEEL
pp.connector.plone-1.0.0.dist-info/entry_points.txt
pp.connector.plone-1.0.0.dist-info/namespace_packages.txt
pp.connector.plone-1.0.0.dist-info/top_level.txt
pp.connector.plone-1.0.0.dist-info/RECORD
