Metadata-Version: 2.1
Name: pp.connector.plone
Version: 1.0.0
Summary: Produce & Publisher Plone Client Connector
Home-page: http://pypi.python.org/pypi/pp.client.plone
Author: Andreas Jung
Author-email: info@zopyx.com
License: GPL
Keywords: PDF Plone Python EBook EPUB
Platform: UNKNOWN
Classifier: Programming Language :: Python
Classifier: Programming Language :: Python :: 2.7
Classifier: Programming Language :: Python :: 3.6
Classifier: Programming Language :: Python :: 3.7
Classifier: Framework :: Plone
Classifier: Framework :: Plone :: 5.1
Classifier: Framework :: Plone :: 5.2
Classifier: Framework :: Zope2
Classifier: Framework :: Zope :: 2
Classifier: Framework :: Zope :: 4
Classifier: Topic :: Software Development :: Libraries :: Python Modules
Requires-Dist: setuptools
Requires-Dist: plone.browserlayer
Requires-Dist: pp.client-python
Requires-Dist: pp.core
Requires-Dist: furl
